hdl/rtl/EF_ADCS1008A.v
/*
	Copyright 2023 Efabless Corp.

	Author: Mohamed Shalan (mshalan@efabless.com)
	
	Licensed under the Apache License, Version 2.0 (the "License"); 
	you may not use this file except in compliance with the License. 
	You may obtain a copy of the License at:
	http://www.apache.org/licenses/LICENSE-2.0
	Unless required by applicable law or agreed to in writing, software 
	distributed under the License is distributed on an "AS IS" BASIS, 
	WITHOUT WARRANTIES OR CONDITIONS OF ANY KIND, either express or implied. 
	See the License for the specific language governing permissions and 
	limitations under the License.
*/
/*
    Sequencer: up to 8 steps; all written to a FIFO (depth=16)
        - Every step: Channel number, Nop and End
    SoC: Timer, EoC or SW
    Sample time is programmable
    Interrupt sources: 
        - Fifo is full 
        - Fifo threshold
        - EoC
*/
module clock_divider #(parameter CLKDIV_WIDTH = 8)(
    input wire clk,
    input wire rst_n,
    input wire en,
    input wire [CLKDIV_WIDTH-1:0] clkdiv,
    output wire clko
);
    reg [CLKDIV_WIDTH-1:0] clkdiv_ctr;
    
    reg clken;

    // Clock Divider
    wire clkdiv_match = (clkdiv_ctr == clkdiv);
    always @(posedge clk or negedge rst_n)
        if(!rst_n)
            clkdiv_ctr <= 'b0;
        else 
            if(clkdiv_match)
                clkdiv_ctr <= 'b0;
            else if(en)
                clkdiv_ctr <= clkdiv_ctr + 'b1;
    always @(posedge clk or negedge rst_n)
        if(!rst_n)
            clken <= 1'b0;
        else
            if(clken) 
                clken <= 1'b0;
            else if(clkdiv_match)
                clken <= 1'b1;

    assign clko = clken;

endmodule

module fifo #(parameter DW=10, AW=5)(
    input     wire            clk,
    input     wire            rst_n,
    input     wire            rd,
    input     wire            wr,
    input     wire [DW-1:0]   w_data,
    output    wire            empty,
    output    wire            full,
    output    wire [DW-1:0]   r_data,
    output    wire [AW-1:0]   level    
);

    localparam  DEPTH = 2**AW;

    //Internal Signal declarations
    reg [DW-1:0]  array_reg [DEPTH-1:0];
    reg [AW-1:0]  w_ptr_reg;
    reg [AW-1:0]  w_ptr_next;
    reg [AW-1:0]  w_ptr_succ;
    reg [AW-1:0]  r_ptr_reg;
    reg [AW-1:0]  r_ptr_next;
    reg [AW-1:0]  r_ptr_succ;

  // Level
    reg [AW-1:0] level_reg;
    reg [AW-1:0] level_next;      
    reg full_reg;
    reg empty_reg;
    reg full_next;
    reg empty_next;
  
  wire w_en;
  

  always @ (posedge clk)
    if(w_en)
    begin
      array_reg[w_ptr_reg] <= w_data;
    end

  assign r_data = array_reg[r_ptr_reg];   

  assign w_en = wr & ~full_reg;           

//State Machine
  always @ (posedge clk, negedge rst_n)
  begin
    if(!rst_n)
      begin
        w_ptr_reg <= 0;
        r_ptr_reg <= 0;
        full_reg <= 1'b0;
        empty_reg <= 1'b1;
        level_reg <= 4'd0;
      end
    else
      begin
        w_ptr_reg <= w_ptr_next;
        r_ptr_reg <= r_ptr_next;
        full_reg <= full_next;
        empty_reg <= empty_next;
        level_reg <= level_next;
      end
  end


//Next State Logic
  always @*
  begin
    w_ptr_succ = w_ptr_reg + 1;
    r_ptr_succ = r_ptr_reg + 1;
    
    w_ptr_next = w_ptr_reg;
    r_ptr_next = r_ptr_reg;
    full_next = full_reg;
    empty_next = empty_reg;
    level_next = level_reg;
    
    case({w_en,rd})
      //2'b00: nop
      2'b01:
        if(~empty_reg)
          begin
            r_ptr_next = r_ptr_succ;
            full_next = 1'b0;
            level_next = level_reg - 1;
            if (r_ptr_succ == w_ptr_reg)
              empty_next = 1'b1;
          end
      2'b10:
        if(~full_reg)
          begin
            w_ptr_next = w_ptr_succ;
            empty_next = 1'b0;
            level_next = level_reg + 1;
            if (w_ptr_succ == r_ptr_reg)
              full_next = 1'b1;
          end
      2'b11:
        begin
          w_ptr_next = w_ptr_succ;
          r_ptr_next = r_ptr_succ;
        end
    endcase
  end

    //Set Full and Empty

  assign full = full_reg;
  assign empty = empty_reg;

  assign level = level_reg;
  
endmodule

module sar_ctrl #(parameter SIZE = 8) ( 
    input   wire                clk,        // The clock
    input   wire                rst_n,      // Active high reset
    input   wire                soc,        // Start of Conversion
    input   wire                cmp,        // Analog comparator output
    input   wire                en,
    input   wire [3:0]          swidth,     // Sample time width in clock cycles
    output  wire                sample_n,   // Sample_n/Hold
    output  wire [SIZE-1:0]     data,       // The output sample
    output  wire                eoc         // End of Conversion
);
	
	reg [SIZE-1:0]  result;
	reg [SIZE-1:0]  shift;
    reg [3:0]       sample_ctr;
    wire            sample_ctr_match = (swidth == sample_ctr);
	
    // FSM to handle the SAR operation
    reg [1:0]   state, nstate;
	localparam [1:0]    IDLE    = 2'd0, 
	                    SAMPLE  = 2'd1, 
	                    CONV    = 2'd2, 
	                    DONE    = 2'd3;

	always @*
        case (state)
            IDLE    :   if(soc) nstate = SAMPLE;
                        else nstate = IDLE;
            SAMPLE  :   if(sample_ctr_match) nstate = CONV;
                        else nstate = SAMPLE;
            CONV    :   if(shift == 1'b1) nstate = DONE;
                        else nstate = CONV;
            DONE    :   nstate = IDLE;
            default:    nstate = IDLE;
        endcase
	  
	always @(posedge clk or negedge rst_n)
        if(!rst_n)
            state <= IDLE;
        else if(en)
            state <= nstate;

    // Sample Counter
    always @(posedge clk or negedge rst_n)
        if(!rst_n)
            sample_ctr <= 'b0;
        else if(en & (state==SAMPLE))
            if(sample_ctr_match)
                sample_ctr <= 'b0;
            else
                sample_ctr <= sample_ctr + 'b1;
    
    // Shift Register
    always @(posedge clk)
        if(en)
            if(state == IDLE) 
                shift <= 1'b1 << (SIZE-1);
            else if(state == CONV)
                shift<= shift >> 1; 

    // The SAR
    wire [SIZE-1:0] current = (cmp == 1'b0) ? ~shift : {SIZE{1'b1}} ;
    wire [SIZE-1:0] next = shift >> 1;
    always @(posedge clk)
        if(en)
            if(state == IDLE) 
                result <= 1'b1 << (SIZE-1);
            else if(state == CONV)
                result <= (result | next) & current; 
	   
	assign data = result;
    
    assign eoc = (state==DONE);

    assign sample_n = (state != SAMPLE);


	
endmodule

/* Sequence is a 5-bit value: 
    - [2:0] : Channel Number
    - [3] : Skip
    - [4] : End
*/

module EF_ADCS1008A #(parameter CLKDIV_WIDTH = 8, FIFO_AW=5)(
    input  wire                     clk,
    input  wire                     rst_n,
    input  wire [3:0]               swidth,
    input  wire [CLKDIV_WIDTH-1:0]  clkdiv, 
    input  wire [CLKDIV_WIDTH-1:0]  sample_div, 
    input  wire                     en,
    input  wire                     cmp,
    input  wire                     soc, 
    output wire                     sample_n,
    output wire                     eoc, 
    output wire [9:0]               data,
    output wire [9:0]               adc_data,
    input  wire                     rd,
    output wire [2:0]               ch_sel_out,
    input  wire [2:0]               ch_sel_in,
    input  wire [4:0]               seq0,
    input  wire [4:0]               seq1,
    input  wire [4:0]               seq2,
    input  wire [4:0]               seq3,
    input  wire [4:0]               seq4,
    input  wire [4:0]               seq5,
    input  wire [4:0]               seq6,
    input  wire [4:0]               seq7,
    input  wire                     seq_en,
    output wire                     fifo_full,
    input  wire [FIFO_AW-1:0]       fifo_threshold,
    output wire                     fifo_above
);
    wire                clken;
    wire                sample_en;
    wire                soc_edge;
    reg  [1:0]          last_soc;
    reg  [2:0]          seq_ctr;
    wire [4:0]          seq;
    reg                 seq_soc;

    wire                fifo_rd;
    wire                fifo_wr;
    wire [9:0]          fifo_wdata;
    wire                fifo_empty;
    //wire            fifo_full;
    wire [9:0]          fifo_rdata;
    wire [FIFO_AW-1:0]  fifo_level;  
    
    // Generate an SoC pulse in synch with clken
    wire start_of_conv = seq_en ? seq_soc : soc;
    always @(posedge clk or negedge rst_n)
        if(!rst_n)
            last_soc <= 0;
        else if(clken)
            last_soc <= {last_soc[0], start_of_conv};
    assign soc_edge = ~last_soc[1] & start_of_conv;


    // Sequencer
    assign seq =    (seq_ctr==0) ? seq0 :
                    (seq_ctr==1) ? seq1 :
                    (seq_ctr==2) ? seq2 :
                    (seq_ctr==3) ? seq3 :
                    (seq_ctr==4) ? seq4 :
                    (seq_ctr==5) ? seq5 :
                    (seq_ctr==6) ? seq6 : seq7;
    wire [2:0] seq_ch = seq[2:0];
    wire seq_end = seq[4];
    wire seq_skip = seq[3];

    always @(posedge clk or negedge rst_n)
            if(!rst_n)
                seq_ctr <= 'b111;
            else
                if(sample_en)
                    if(seq_end)
                        seq_ctr <= 'b0;
                    else
                        seq_ctr <= seq_ctr + 'b1;
    
    assign ch_sel_out = seq_en ? seq_ch : ch_sel_in;

    always @(posedge clk or negedge rst_n)
        if(!rst_n) seq_soc = 'b0;
        else if(sample_en) seq_soc = 'b1;
        else if(clken) seq_soc = 'b0;
    
    // Clock Dividers
    clock_divider CDIV (
        .clk(clk),
        .rst_n(rst_n),
        .en(en),
        .clkdiv(clkdiv),
        .clko(clken)
    );
    
    clock_divider SDIV (
        .clk(clk),
        .rst_n(rst_n),
        .en(clken & seq_en),
        .clkdiv(sample_div),
        .clko(sample_en)
    );

    sar_ctrl #(.SIZE(10)) SAR ( 
        .clk(clk),        
        .rst_n(rst_n),      
        .soc(soc_edge),        
        .cmp(cmp),        
        .en(clken),         
        .swidth(swidth),     
        .sample_n(sample_n),       
        .data(fifo_wdata),       
        .eoc(eoc)         
    );

    // FIFO
    reg fifo_wr_reg;
    always @(posedge clk or negedge rst_n)
        if(!rst_n) fifo_wr_reg <= 0;
        else fifo_wr_reg <= eoc;
    assign fifo_wr = eoc & ~fifo_wr_reg;
    assign fifo_rd = rd;
    assign data = fifo_rdata;

    assign fifo_above = (fifo_threshold < fifo_level);

    fifo #(.AW(FIFO_AW)) ADCFIFO (
        .clk(clk),
        .rst_n(rst_n),
        .rd(fifo_rd),
        .wr(fifo_wr),
        .w_data(fifo_wdata),
        .empty(fifo_empty),
        .full(fifo_full),
        .r_data(fifo_rdata),
        .level (fifo_level)
    ); 

    assign adc_data = fifo_wdata;

endmodule

hdl/sim/EF_ADCS1008NC.v
/*
	Copyright 2023 Efabless Corp.

	Author: Mohamed Shalan (mshalan@efabless.com)
	
	Licensed under the Apache License, Version 2.0 (the "License"); 
	you may not use this file except in compliance with the License. 
	You may obtain a copy of the License at:
	http://www.apache.org/licenses/LICENSE-2.0
	Unless required by applicable law or agreed to in writing, software 
	distributed under the License is distributed on an "AS IS" BASIS, 
	WITHOUT WARRANTIES OR CONDITIONS OF ANY KIND, either express or implied. 
	See the License for the specific language governing permissions and 
	limitations under the License.
*/
module EF_ADCS1008NC (
    input real          VDD,
    input real          VSS,
    input real          DVDD,
    input real          DVSS,

    input real          VH,
    input real          VL,

    input real          in0,
    input real          in1,
    input real          in2,
    input real          in3,
    input real          in4,
    input real          in5,
    input real          in6,
    input real          in7,

    input wire          hold,
    
    input wire          b0,
    input wire          b1,
    input wire          b2,
    
    input  wire [9:0]   data,
        
    output wire         cmp

);


    wire real a_mux;
    assign a_mux =  ({b2,b1,b0} == 3'd0) ? in0 :
                    ({b2,b1,b0} == 3'd1) ? in1 :
                    ({b2,b1,b0} == 3'd2) ? in2 :
                    ({b2,b1,b0} == 3'd3) ? in3 :
                    ({b2,b1,b0} == 3'd4) ? in4 :
                    ({b2,b1,b0} == 3'd5) ? in5 :
                    ({b2,b1,b0} == 3'd6) ? in6 : in7;

    real held_value;
    always @(posedge hold)
        held_value = a_mux;

    wire real dac_out;
    assign dac_out = data * (VH-VL)/1024.0;

    assign cmp = (held_value > dac_out) ? 1 : 0;

endmodule

verify/utb/EF_ADCS1008A_tb.v
/*
	Copyright 2023 Efabless Corp.

	Author: Mohamed Shalan (mshalan@efabless.com)
	
	Licensed under the Apache License, Version 2.0 (the "License"); 
	you may not use this file except in compliance with the License. 
	You may obtain a copy of the License at:
	http://www.apache.org/licenses/LICENSE-2.0
	Unless required by applicable law or agreed to in writing, software 
	distributed under the License is distributed on an "AS IS" BASIS, 
	WITHOUT WARRANTIES OR CONDITIONS OF ANY KIND, either express or implied. 
	See the License for the specific language governing permissions and 
	limitations under the License.
*/
/*
    A testbench for EF_ADCS0808A: 8-channel, 8-bit SAR ADC with advanced controller and FIFO.
*/
module EF_ADCS1008A_tb;

    reg         clk, rst_n;
    reg [7:0]   clkdiv;
    reg [7:0]   sample_div;
    reg         en;
    wire        sample_n, cmp;
    wire        real vin;
    real        vref=3.3;
    wire [9:0]  data;
    wire [9:0]  adc_data;
    wire        eoc;
    reg         soc;
    reg [3:0]   swidth;

    wire [2:0]  ch_sel_out;
    reg [2:0]   ch_sel_in;
    reg [4:0]   seq0;
    reg [4:0]   seq1;
    reg [4:0]   seq2;
    reg [4:0]   seq3;
    reg [4:0]   seq4;
    reg [4:0]   seq5;
    reg [4:0]   seq6;
    reg [4:0]   seq7;
    reg         seq_en;

    reg         rd;

    wire        fifo_full;
    reg [4:0]   fifo_threshold;
    wire        fifo_above;

    real          in0 = 0.5;
    real          in1 = 1.0;
    real          in2 = 1.5;
    real          in3 = 2.0;
    real          in4 = 2.5;
    real          in5 = 3.0;
    real          in6 = 3.1;
    real          in7 = 3.2;

    // clock
    initial clk = 0;
    always #5 clk <= !clk;

    initial begin
        $dumpfile("EF_ADCS1008A_tb.vcd");
        $dumpvars;
    end

    initial begin
        rst_n = 0;
        clkdiv = 2;
        sample_div = 16;
        en = 1;
        soc = 0;
        swidth = 2;
        seq0 = 5'b00000;    // channel 0 - continue
        seq1 = 5'b00001;    // channel 1 - continue
        seq2 = 5'b00010;    // channel 2 - continue
        seq3 = 5'b10011;    // channel 3 - Stop
        seq_en = 1;
        ch_sel_in = 7;
        fifo_threshold = 5;
        rd = 0;
        #100;
        @(posedge clk); 
        rst_n = 1;
        #300;
        #4000;
        
        // Stop the sequencer
        @(posedge clk); 
        seq_en = 0;

        // Read the data from the FIFO
        repeat (8) begin
            @(posedge clk);
            rd = 1;
            $display("ADC data: %d", data);
            @(posedge clk);
            rd = 0;
        end

        #1000;
        @(posedge clk); 
        soc = 0;
        @(posedge clk); 
        soc = 1;
        #1000;
        $finish;
    end

    wire real VH = vref;
    wire real VL = 0.0;

    EF_ADCS1008NC DAC_ANA (
        .VDD(VDD),
        .VSS(VSS),
        .DVDD(DVDD),
        .DVSS(DVSS),
        .VH(VH),
        .VL(VL),
        .in0(in0),
        .in1(in1),
        .in2(in2),
        .in3(in3),
        .in4(in4),
        .in5(in5),
        .in6(in6),
        .in7(in7),
        .hold(sample_n),
        .b0(ch_sel_out[0]),
        .b1(ch_sel_out[1]),
        .b2(ch_sel_out[2]),
        .data(adc_data),
        .cmp(cmp)
);

    EF_ADCS1008A ADC_CTRL (
        .clk(clk),
        .rst_n(rst_n),
        .clkdiv(clkdiv),
        .sample_div(sample_div),
        .en(en),
        .sample_n(sample_n),
        .data(data),
        .adc_data(adc_data),
        .cmp(cmp),
        .soc(soc),
        .eoc(eoc),
        .swidth(swidth),
        .ch_sel_out(ch_sel_out),
        .ch_sel_in(ch_sel_in),
        .seq0(seq0),
        .seq1(seq1),
        .seq2(seq2),
        .seq3(seq3),
        .seq4(seq4),
        .seq5(seq5),
        .seq6(seq6),
        .seq7(seq7),
        .seq_en(seq_en),
        .rd(rd),
        .fifo_full(fifo_full),
        .fifo_threshold(fifo_threshold),
        .fifo_above(fifo_above)
    );
endmodule

verify/utb/EF_ADCS1008A_tb.vcd
$date
	Mon Sep  4 16:52:06 2023
$end
$version
	Icarus Verilog
$end
$timescale
	1s
$end
$scope module EF_ADCS1008A_tb $end
$var wire 1 ! DVDD $end
$var wire 1 " DVSS $end
$var wire 1 # VDD $end
$var wire 1 $ VSS $end
$var wire 1 % sample_n $end
$var wire 1 & fifo_full $end
$var wire 1 ' fifo_above $end
$var wire 1 ( eoc $end
$var wire 10 ) data [9:0] $end
$var wire 1 * cmp $end
$var wire 3 + ch_sel_out [2:0] $end
$var wire 10 , adc_data [9:0] $end
$var reg 3 - ch_sel_in [2:0] $end
$var reg 1 . clk $end
$var reg 8 / clkdiv [7:0] $end
$var reg 1 0 en $end
$var reg 5 1 fifo_threshold [4:0] $end
$var reg 1 2 rd $end
$var reg 1 3 rst_n $end
$var reg 8 4 sample_div [7:0] $end
$var reg 5 5 seq0 [4:0] $end
$var reg 5 6 seq1 [4:0] $end
$var reg 5 7 seq2 [4:0] $end
$var reg 5 8 seq3 [4:0] $end
$var reg 5 9 seq4 [4:0] $end
$var reg 5 : seq5 [4:0] $end
$var reg 5 ; seq6 [4:0] $end
$var reg 5 < seq7 [4:0] $end
$var reg 1 = seq_en $end
$var reg 1 > soc $end
$var reg 4 ? swidth [3:0] $end
$var real 1 @ VL $end
$var real 1 A in0 $end
$var real 1 B in1 $end
$var real 1 C in2 $end
$var real 1 D in3 $end
$var real 1 E in4 $end
$var real 1 F in5 $end
$var real 1 G in6 $end
$var real 1 H in7 $end
$var real 1 I vref $end
$var real 1 J VH $end
$scope module ADC_CTRL $end
$var wire 10 K adc_data [9:0] $end
$var wire 3 L ch_sel_in [2:0] $end
$var wire 1 . clk $end
$var wire 8 M clkdiv [7:0] $end
$var wire 10 N data [9:0] $end
$var wire 1 0 en $end
$var wire 1 O fifo_rd $end
$var wire 5 P fifo_threshold [4:0] $end
$var wire 1 Q fifo_wr $end
$var wire 1 2 rd $end
$var wire 1 3 rst_n $end
$var wire 8 R sample_div [7:0] $end
$var wire 5 S seq0 [4:0] $end
$var wire 5 T seq1 [4:0] $end
$var wire 5 U seq2 [4:0] $end
$var wire 5 V seq3 [4:0] $end
$var wire 5 W seq4 [4:0] $end
$var wire 5 X seq5 [4:0] $end
$var wire 5 Y seq6 [4:0] $end
$var wire 5 Z seq7 [4:0] $end
$var wire 1 = seq_en $end
$var wire 1 > soc $end
$var wire 1 [ soc_edge $end
$var wire 4 \ swidth [3:0] $end
$var wire 1 ] start_of_conv $end
$var wire 1 ^ seq_skip $end
$var wire 1 _ seq_end $end
$var wire 3 ` seq_ch [2:0] $end
$var wire 5 a seq [4:0] $end
$var wire 1 % sample_n $end
$var wire 1 b sample_en $end
$var wire 10 c fifo_wdata [9:0] $end
$var wire 10 d fifo_rdata [9:0] $end
$var wire 5 e fifo_level [4:0] $end
$var wire 1 & fifo_full $end
$var wire 1 f fifo_empty $end
$var wire 1 ' fifo_above $end
$var wire 1 ( eoc $end
$var wire 1 * cmp $end
$var wire 1 g clken $end
$var wire 3 h ch_sel_out [2:0] $end
$var reg 1 i fifo_wr_reg $end
$var reg 2 j last_soc [1:0] $end
$var reg 3 k seq_ctr [2:0] $end
$var reg 1 l seq_soc $end
$scope module ADCFIFO $end
$var wire 1 . clk $end
$var wire 1 f empty $end
$var wire 1 & full $end
$var wire 10 m r_data [9:0] $end
$var wire 1 O rd $end
$var wire 1 3 rst_n $end
$var wire 1 n w_en $end
$var wire 1 Q wr $end
$var wire 10 o w_data [9:0] $end
$var wire 5 p level [4:0] $end
$var reg 1 q empty_next $end
$var reg 1 r empty_reg $end
$var reg 1 s full_next $end
$var reg 1 t full_reg $end
$var reg 5 u level_next [4:0] $end
$var reg 5 v level_reg [4:0] $end
$var reg 5 w r_ptr_next [4:0] $end
$var reg 5 x r_ptr_reg [4:0] $end
$var reg 5 y r_ptr_succ [4:0] $end
$var reg 5 z w_ptr_next [4:0] $end
$var reg 5 { w_ptr_reg [4:0] $end
$var reg 5 | w_ptr_succ [4:0] $end
$upscope $end
$scope module CDIV $end
$var wire 1 . clk $end
$var wire 8 } clkdiv [7:0] $end
$var wire 1 g clko $end
$var wire 1 0 en $end
$var wire 1 3 rst_n $end
$var wire 1 ~ clkdiv_match $end
$var reg 8 !" clkdiv_ctr [7:0] $end
$var reg 1 g clken $end
$upscope $end
$scope module SAR $end
$var wire 1 . clk $end
$var wire 1 g en $end
$var wire 1 3 rst_n $end
$var wire 1 [ soc $end
$var wire 4 "" swidth [3:0] $end
$var wire 1 % sample_n $end
$var wire 1 #" sample_ctr_match $end
$var wire 10 $" next [9:0] $end
$var wire 1 ( eoc $end
$var wire 10 %" data [9:0] $end
$var wire 10 &" current [9:0] $end
$var wire 1 * cmp $end
$var reg 2 '" nstate [1:0] $end
$var reg 10 (" result [9:0] $end
$var reg 4 )" sample_ctr [3:0] $end
$var reg 10 *" shift [9:0] $end
$var reg 2 +" state [1:0] $end
$upscope $end
$scope module SDIV $end
$var wire 1 . clk $end
$var wire 8 ," clkdiv [7:0] $end
$var wire 1 b clko $end
$var wire 1 -" en $end
$var wire 1 3 rst_n $end
$var wire 1 ." clkdiv_match $end
$var reg 8 /" clkdiv_ctr [7:0] $end
$var reg 1 0" clken $end
$upscope $end
$upscope $end
$scope module DAC_ANA $end
$var wire 1 1" b0 $end
$var wire 1 2" b1 $end
$var wire 1 3" b2 $end
$var wire 10 4" data [9:0] $end
$var wire 1 % hold $end
$var wire 1 * cmp $end
$var real 1 5" DVDD $end
$var real 1 6" DVSS $end
$var real 1 7" VDD $end
$var real 1 8" VH $end
$var real 1 9" VL $end
$var real 1 :" VSS $end
$var real 1 ;" held_value $end
$var real 1 <" in0 $end
$var real 1 =" in1 $end
$var real 1 >" in2 $end
$var real 1 ?" in3 $end
$var real 1 @" in4 $end
$var real 1 A" in5 $end
$var real 1 B" in6 $end
$var real 1 C" in7 $end
$var real 1 D" dac_out $end
$var real 1 E" a_mux $end
$upscope $end
$upscope $end
$enddefinitions $end
#0
$dumpvars
r0 E"
r0 D"
r3.2 C"
r3.1 B"
r3 A"
r2.5 @"
r2 ?"
r1.5 >"
r1 ="
r0.5 <"
r0 ;"
r0 :"
r0 9"
r3.3 8"
r0 7"
r0 6"
r0 5"
bx 4"
x3"
x2"
x1"
00"
b0 /"
0."
0-"
b10000 ,"
b0 +"
bx *"
b0 )"
bx ("
b0 '"
bx &"
bx %"
b0xxxxxxxxx $"
0#"
b10 ""
b0 !"
0~
b10 }
b1 |
b0 {
b0 z
b1 y
b0 x
b0 w
b0 v
b0 u
0t
0s
1r
1q
b0 p
bx o
0n
bx m
0l
b111 k
b0 j
0i
bx h
0g
1f
b0 e
bx d
bx c
0b
bx a
bx `
x_
x^
0]
b10 \
0[
bx Z
bx Y
bx X
bx W
b10011 V
b10 U
b1 T
b0 S
b10000 R
0Q
b101 P
0O
bx N
b10 M
b111 L
bx K
r3.3 J
r3.3 I
r3.2 H
r3.1 G
r3 F
r2.5 E
r2 D
r1.5 C
r1 B
r0.5 A
r0 @
b10 ?
0>
1=
bx <
bx ;
bx :
bx 9
b10011 8
b10 7
b1 6
b0 5
b10000 4
03
02
b101 1
10
b10 /
0.
b111 -
bx ,
bx +
0*
bx )
0(
0'
0&
1%
z$
z#
z"
z!
$end
#5
1.
#10
0.
#15
1.
#20
0.
#25
1.
#30
0.
#35
1.
#40
0.
#45
1.
#50
0.
#55
1.
#60
0.
#65
1.
#70
0.
#75
1.
#80
0.
#85
1.
#90
0.
#95
1.
#100
0.
#105
b1 !"
13
1.
#110
0.
#115
1~
b10 !"
1.
#120
0.
#125
1-"
1g
0~
b0 !"
1.
#130
0.
#135
b111111111 &"
0-"
b100000000 $"
b1 !"
0g
b1 /"
r1.65 D"
b1000000000 ,
b1000000000 K
b1000000000 4"
b1000000000 c
b1000000000 o
b1000000000 %"
b1000000000 ("
b1000000000 *"
1.
#140
0.
#145
1~
b10 !"
1.
#150
0.
#155
1-"
0~
b0 !"
1g
1.
#160
0.
#165
0-"
b10 /"
0g
b1 !"
1.
#170
0.
#175
1~
b10 !"
1.
#180
0.
#185
1-"
1g
0~
b0 !"
1.
#190
0.
#195
0-"
b1 !"
0g
b11 /"
1.
#200
0.
#205
1~
b10 !"
1.
#210
0.
#215
1-"
0~
b0 !"
1g
1.
#220
0.
#225
0-"
b100 /"
0g
b1 !"
1.
#230
0.
#235
1~
b10 !"
1.
#240
0.
#245
1-"
1g
0~
b0 !"
1.
#250
0.
#255
0-"
b1 !"
0g
b101 /"
1.
#260
0.
#265
1~
b10 !"
1.
#270
0.
#275
1-"
0~
b0 !"
1g
1.
#280
0.
#285
0-"
b110 /"
0g
b1 !"
1.
#290
0.
#295
1~
b10 !"
1.
#300
0.
#305
1-"
1g
0~
b0 !"
1.
#310
0.
#315
0-"
b1 !"
0g
b111 /"
1.
#320
0.
#325
1~
b10 !"
1.
#330
0.
#335
1-"
0~
b0 !"
1g
1.
#340
0.
#345
0-"
b1000 /"
0g
b1 !"
1.
#350
0.
#355
1~
b10 !"
1.
#360
0.
#365
1-"
1g
0~
b0 !"
1.
#370
0.
#375
0-"
b1 !"
0g
b1001 /"
1.
#380
0.
#385
1~
b10 !"
1.
#390
0.
#395
1-"
0~
b0 !"
1g
1.
#400
0.
#405
0-"
b1010 /"
0g
b1 !"
1.
#410
0.
#415
1~
b10 !"
1.
#420
0.
#425
1-"
1g
0~
b0 !"
1.
#430
0.
#435
0-"
b1 !"
0g
b1011 /"
1.
#440
0.
#445
1~
b10 !"
1.
#450
0.
#455
1-"
0~
b0 !"
1g
1.
#460
0.
#465
0-"
b1100 /"
0g
b1 !"
1.
#470
0.
#475
1~
b10 !"
1.
#480
0.
#485
1-"
1g
0~
b0 !"
1.
#490
0.
#495
0-"
b1 !"
0g
b1101 /"
1.
#500
0.
#505
1~
b10 !"
1.
#510
0.
#515
1-"
0~
b0 !"
1g
1.
#520
0.
#525
0-"
b1110 /"
0g
b1 !"
1.
#530
0.
#535
1~
b10 !"
1.
#540
0.
#545
1-"
1g
0~
b0 !"
1.
#550
0.
#555
0-"
b1 !"
0g
b1111 /"
1.
#560
0.
#565
1~
b10 !"
1.
#570
0.
#575
1-"
0~
b0 !"
1g
1.
#580
0.
#585
0-"
1."
b10000 /"
0g
b1 !"
1.
#590
0.
#595
1~
b10 !"
0."
b0 /"
1b
10"
1.
#600
0.
#605
r0.5 E"
03"
02"
01"
b0 +
b0 h
b0 `
0_
0^
b0 a
1-"
b0 k
0b
00"
1g
0~
b0 !"
b1 '"
1[
1]
1l
1.
#610
0.
#615
0-"
b1 !"
0g
b1 /"
0%
b1 +"
b1 j
b1 '"
0[
0]
0l
1.
#620
0.
#625
1~
b10 !"
1.
#630
0.
#635
1-"
0~
b0 !"
1g
1.
#640
0.
#645
0-"
b10 j
b1 )"
b10 /"
0g
b1 !"
1.
#650
0.
#655
1~
b10 !"
1.
#660
0.
#665
1-"
1g
0~
b0 !"
1.
#670
0.
#675
0-"
b10 '"
b1 !"
0g
b11 /"
1#"
b10 )"
b0 j
1.
#680
0.
#685
1~
b10 !"
1.
#690
0.
#695
1-"
0~
b0 !"
1g
1.
#700
0.
#705
r0.5 ;"
0-"
0#"
b0 )"
1%
b10 +"
b100 /"
0g
b1 !"
1.
#710
0.
#715
1~
b10 !"
1.
#720
0.
#725
1-"
1g
0~
b0 !"
1.
#730
0.
#735
b1011111111 &"
0-"
b10000000 $"
b1 !"
0g
b101 /"
r0.825 D"
b100000000 ,
b100000000 K
b100000000 4"
b100000000 c
b100000000 o
b100000000 %"
b100000000 ("
b100000000 *"
1.
#740
0.
#745
1~
b10 !"
1.
#750
0.
#755
1-"
0~
b0 !"
1g
1.
#760
0.
#765
b1111111111 &"
1*
0-"
b1000000 $"
b110 /"
0g
b1 !"
b10000000 *"
r0.4125 D"
b10000000 ,
b10000000 K
b10000000 4"
b10000000 c
b10000000 o
b10000000 %"
b10000000 ("
1.
#770
0.
#775
1~
b10 !"
1.
#780
0.
#785
1-"
1g
0~
b0 !"
1.
#790
0.
#795
b1110111111 &"
0*
0-"
b100000 $"
b1 !"
0g
b111 /"
r0.6187499999999999 D"
b11000000 ,
b11000000 K
b11000000 4"
b11000000 c
b11000000 o
b11000000 %"
b11000000 ("
b1000000 *"
1.
#800
0.
#805
1~
b10 !"
1.
#810
0.
#815
1-"
0~
b0 !"
1g
1.
#820
0.
#825
b1111011111 &"
0-"
b10000 $"
b1000 /"
0g
b1 !"
b100000 *"
r0.515625 D"
b10100000 ,
b10100000 K
b10100000 4"
b10100000 c
b10100000 o
b10100000 %"
b10100000 ("
1.
#830
0.
#835
1~
b10 !"
1.
#840
0.
#845
1-"
1g
0~
b0 !"
1.
#850
0.
#855
1*
b1111111111 &"
0-"
b1000 $"
b1 !"
0g
b1001 /"
r0.4640625 D"
b10010000 ,
b10010000 K
b10010000 4"
b10010000 c
b10010000 o
b10010000 %"
b10010000 ("
b10000 *"
1.
#860
0.
#865
1~
b10 !"
1.
#870
0.
#875
1-"
0~
b0 !"
1g
1.
#880
0.
#885
0-"
b100 $"
b1010 /"
0g
b1 !"
b1000 *"
r0.48984375 D"
b10011000 ,
b10011000 K
b10011000 4"
b10011000 c
b10011000 o
b10011000 %"
b10011000 ("
1.
#890
0.
#895
1~
b10 !"
1.
#900
0.
#905
1-"
1g
0~
b0 !"
1.
#910
0.
#915
b1111111011 &"
0*
0-"
b10 $"
b1 !"
0g
b1011 /"
r0.502734375 D"
b10011100 ,
b10011100 K
b10011100 4"
b10011100 c
b10011100 o
b10011100 %"
b10011100 ("
b100 *"
1.
#920
0.
#925
1~
b10 !"
1.
#930
0.
#935
1-"
0~
b0 !"
1g
1.
#940
0.
#945
b1111111111 &"
1*
0-"
b1 $"
b1100 /"
0g
b1 !"
b10 *"
r0.4962890625 D"
b10011010 ,
b10011010 K
b10011010 4"
b10011010 c
b10011010 o
b10011010 %"
b10011010 ("
1.
#950
0.
#955
1~
b10 !"
1.
#960
0.
#965
1-"
1g
0~
b0 !"
1.
#970
0.
#975
0-"
b11 '"
b0 $"
b1 !"
0g
b1101 /"
r0.49951171875 D"
b10011011 ,
b10011011 K
b10011011 4"
b10011011 c
b10011011 o
b10011011 %"
b10011011 ("
b1 *"
1.
#980
0.
#985
1~
b10 !"
1.
#990
0.
#995
1-"
0~
b0 !"
1g
1.
#1000
0.
#1005
b1 u
0q
b1 z
1n
1Q
0-"
b0 '"
1(
b11 +"
b1110 /"
0g
b1 !"
b0 *"
1.
#1010
0.
